src/prmcu_uart/prmcu_uart_top.vhd
-----------------------------------------------------------------
-- Name : prmcu_uart.vhdl
-----------------------------------------------------------------
-- Description : Module designed to serve as uart controller. It
-- enables simultaneous reception and transmission of uart data.
-- Module consist of 32 x 8 rx\tx fifos.
-----------------------------------------------------------------
-- Author : Piotr Radecki
-----------------------------------------------------------------
-- Edited : January 2022
-----------------------------------------------------------------
library ieee;
use ieee.std_logic_1164.all;
use ieee.numeric_std.all;

entity prmcu_uart_top is
	port(
		clk                  : in  std_logic;
		internal_clk_o       : out std_logic;
		rst                  : in  std_logic;

		-- control
		uart_en              : in  std_logic;
		tx_en                : in  std_logic;
		rx_en                : in  std_logic;
		n_parity_bits        : in  std_logic; 
		n_stop_bits          : in  std_logic_vector(1 downto 0); 
		n_data_bits          : in  std_logic_vector(3 downto 0); 
		internal_clk_divider : in  std_logic_vector(7 downto 0);
  
		--input axi interface
		in_dat_i             : in  std_logic_vector(8 downto 0);
		in_vld_i             : in  std_logic;
		in_rdy_o             : in  std_logic;

		-- output axi interface
		out_dat_o            : out std_logic_vector(8 downto 0);
		out_vld_o            : out std_logic;
		out_rdy_i            : in  std_logic;

		--to external device
		tx_o                 : out std_logic;
		rx_i                 : in  std_logic
	);
end entity prmcu_uart_top;
	
architecture rtl of prmcu_uart_top is
	
	component prmcu_uart_transmitter is 
		port(
			clk            : in  std_logic;
			internal_clk_i : in  std_logic;
			rst            : in  std_logic;
			tx_en          : in  std_logic;
			n_parity_btis  : in  std_logic;
			n_stop_bits    : in  std_logic_vector(1 downto 0);
			
			in_dat_i       : in  std_logic_vector(8 downto 0);
			in_vld_i       : in  std_logic;
			in_rdy_o       : out std_logic;

			tx_o           : out std_logic
		);
	end component;


			
begin
	tx_o <= '1';
 
end rtl;

verif/uart_verif/uart_tb.sv
`timescale 1ns/1ps
 
/*Assumption is that input clk has f=10MHz*/
module tb;
	int n_writes = 20;
	bit [8:0] in_dat_buffer [100];
	bit [2:0] in_overhead_buffer [100];

	bit [8:0] tx_dat_buffer [100];
	bit [2:0] tx_overhead_buffer [100];
	int tx_written = 0;
	int error_cnt = 0;
	int sc_i = 0;
	
	reg external_clk;

	reg        clk;
	wire       internal_clk;
	reg        rst;

	reg        uart_en;
	reg        tx_en;
	reg        rx_en;
	reg        n_parity_bits;
	reg  [1:0] n_stop_bits;
	reg  [3:0] n_data_bits;
	reg  [7:0] internal_clk_divider;

	reg  [8:0] in_dat;
	reg        in_vld;
	wire       in_rdy;

	wire [8:0] out_dat;
	wire       out_vld;
	reg        out_rdy;

	wire      tx;
	reg       rx;


	/*DUT declaration*/
	prmcu_uart_top dut(
		.clk(clk),
		.internal_clk_o(internal_clk),
		.rst(rst),

		.uart_en(uart_en),
		.tx_en(tx_en),
		.rx_en(rx_en),
		.n_parity_bits(n_parity_bits),
		.n_stop_bits(n_stop_bits),
		.n_data_bits(n_data_bits),
		.internal_clk_divider(internal_clk_divider),

		.in_dat_i(in_dat),
		.in_vld_i(in_vld),
		.in_rdy_o(in_rdy),
		
		.out_dat_o(out_dat),
		.out_vld_o(out_vld),
		.out_rdy_i(out_rdy),

		.tx_o(tx),
		.rx_i(rx)
	);

	
	/*10MHz*/
	always #50 clk =~ clk;

	/*113.6 kbaud*/
	always #4400 external_clk =~ clk;
	
	/*Clock stimulous*/
	initial begin
		clk <= 0;
		external_clk <= 0;
		rst <= 1;
		#100 
		rst <= 0;
		uart_en <= 1;
		tx_en <= 1;
		rx_en <= 0;
		n_parity_bits <= 0;
		n_stop_bits <= 1;
		n_data_bits <= 8;
		internal_clk_divider <= 43; /*115200*/ /*div - 2*43*/
		
		
		#1000000 
		if (error_cnt > 0) begin
			$display("Sumlation FAILED!");
		end else begin
			$display("Simulation PASSED!");
		end
		$finish;

	end

	/*dump*/
	initial begin
		$dumpvars;
		$dumpfile("uart_dump.vcd");
	end

	/*write (in_dat) generator and driver*/
	initial begin
		in_vld <= 0;
		#350
		in_vld <= 1;
		for (int i = 0; i < n_writes; i++) begin
			in_dat[8] = 0;
			in_dat[7:0] = $urandom();

			@(posedge clk & in_rdy == 1);
		end
	end


	/*monitor in_dat_part*/
	initial begin
		for (int i = 0; i < n_writes; i++) begin
			@(posedge clk & in_vld == 1 & in_rdy == 1)
			in_dat_buffer[i] = in_dat;
			in_overhead_buffer[i] = {n_parity_bits, n_stop_bits};
		end
	end

	/*monitor in tx part*/
	initial begin
		@(tx == 1);
		for (int i = 0; i < n_writes; i++) begin 
			@(posedge external_clk & tx == 0);
			for (int i = 0; i < n_data_bits; i++) begin
				@(posedge external_clk);
				tx_dat_buffer[i] = tx;
			end
			for (int i = 0; i < n_parity_bits+n_stop_bits; i++) begin
				@(posedge external_clk);
				tx_overhead_buffer[i] = tx;
			end
			tx_written = 1;
		end
	end

	/*scoreboard*/
	
	initial begin
		for (sc_i = 0; sc_i < n_writes; sc_i++) begin
			@(tx_written == 1);
			tx_written = 0;
			if (tx_dat_buffer[sc_i] == in_dat_buffer[sc_i]) begin
        		if (tx_overhead_buffer[sc_i] == in_overhead_buffer[sc_i]) begin
            		$display("T=%0t [Scoreboard] PASS! addr = 0x%0h", $time, sc_i);
				end else begin
					$display("T=%0t [Scoreboard] ERROR! overhead mismatch addr = 0x%0h expected = %0b received = %0b",
				         	$time, sc_i, in_overhead_buffer[sc_i], tx_overhead_buffer[sc_i]);
					error_cnt = error_cnt + 1;
				end 
			end else begin
				$display("T=%0t [Scoreboard] ERROR! data mismatch addr = 0x%0h expected = 0x%0h received = 0x%0h",
				         $time, sc_i, in_dat_buffer[sc_i], tx_dat_buffer[sc_i]);
			end
		end
	end
	
	initial begin
		#100000	
		if(sc_i < n_writes-1) begin
    		$display("T=%0t [Scoreboard] ERROR! Not all data has been captured. Captured frames: %0d", $time, sc_i);
			error_cnt = error_cnt + 1;
		end
	end
	

endmodule

verif/uart_verif/build/dump.vcd
$date
	Fri Jan 14 14:31:43 2022
$end
$version
	Icarus Verilog
$end
$timescale
	1ps
$end
$scope module tb $end
$var wire 1 ! in_rdy $end
$var wire 1 " internal_clk $end
$var wire 9 # out_dat [8:0] $end
$var wire 1 $ out_vld $end
$var wire 1 % tx $end
$var reg 1 & clk $end
$var reg 1 ' external_clk $end
$var reg 9 ( in_dat [8:0] $end
$var reg 1 ) in_vld $end
$var reg 8 * internal_clk_divider [7:0] $end
$var reg 4 + n_data_bits [3:0] $end
$var reg 1 , n_parity_bits $end
$var reg 2 - n_stop_bits [1:0] $end
$var reg 1 . out_rdy $end
$var reg 1 / rst $end
$var reg 1 0 rx $end
$var reg 1 1 rx_en $end
$var reg 1 2 tx_en $end
$var reg 1 3 uart_en $end
$var integer 32 4 error_cnt [31:0] $end
$var integer 32 5 n_writes [31:0] $end
$var integer 32 6 sc_i [31:0] $end
$var integer 32 7 tx_written [31:0] $end
$scope module dut $end
$var wire 1 & clk $end
$var wire 9 8 in_dat_i [8:0] $end
$var wire 1 ! in_rdy_o $end
$var wire 1 ) in_vld_i $end
$var wire 8 9 internal_clk_divider [7:0] $end
$var wire 1 " internal_clk_o $end
$var wire 4 : n_data_bits [3:0] $end
$var wire 1 , n_parity_bits $end
$var wire 2 ; n_stop_bits [1:0] $end
$var wire 9 < out_dat_o [8:0] $end
$var wire 1 . out_rdy_i $end
$var wire 1 $ out_vld_o $end
$var wire 1 / rst $end
$var wire 1 1 rx_en $end
$var wire 1 0 rx_i $end
$var wire 1 2 tx_en $end
$var wire 1 % tx_o $end
$var wire 1 3 uart_en $end
$upscope $end
$scope begin $ivl_for_loop0 $end
$var integer 32 = i [31:0] $end
$upscope $end
$scope begin $ivl_for_loop1 $end
$var integer 32 > i [31:0] $end
$upscope $end
$scope begin $ivl_for_loop2 $end
$var integer 32 ? i [31:0] $end
$scope begin $ivl_for_loop3 $end
$var integer 32 @ i [31:0] $end
$upscope $end
$scope begin $ivl_for_loop4 $end
$var integer 32 A i [31:0] $end
$upscope $end
$upscope $end
$upscope $end
$enddefinitions $end
#0
$dumpvars
b0 A
b0 @
b0 ?
b0 >
b0 =
bz <
bx ;
bx :
bx 9
bx 8
b0 7
b0 6
b10100 5
b0 4
x3
x2
x1
x0
1/
x.
bx -
x,
bx +
bx *
0)
bx (
0'
0&
1%
z$
bz #
z"
z!
$end
#50000
1&
#100000
b101011 *
b101011 9
b1000 +
b1000 :
b1 -
b1 ;
0,
01
12
13
0/
0&
#150000
1&
#200000
0&
#250000
1&
#300000
0&
#350000
b1 >
1)
b1 =
1&
b10000001 (
b10000001 8
#400000
0&
#450000
b10 >
b1001 (
b1001 8
b10 =
1&
#500000
0&
#550000
b11 >
b1100011 (
b1100011 8
b11 =
1&
#600000
0&
#650000
b100 >
b1101 (
b1101 8
b100 =
1&
#700000
0&
#750000
b101 >
b10001101 (
b10001101 8
b101 =
1&
#800000
0&
#850000
b110 >
b1100101 (
b1100101 8
b110 =
1&
#900000
0&
#950000
b111 >
b10010 (
b10010 8
b111 =
1&
#1000000
0&
#1050000
b1000 >
b1 (
b1 8
b1000 =
1&
#1100000
0&
#1150000
b1001 >
b1101 (
b1101 8
b1001 =
1&
#1200000
0&
#1250000
b1010 >
b1110110 (
b1110110 8
b1010 =
1&
#1300000
0&
#1350000
b1011 >
b111101 (
b111101 8
b1011 =
1&
#1400000
0&
#1450000
b1100 >
b11101101 (
b11101101 8
b1100 =
1&
#1500000
0&
#1550000
b1101 >
b10001100 (
b10001100 8
b1101 =
1&
#1600000
0&
#1650000
b1110 >
b11111001 (
b11111001 8
b1110 =
1&
#1700000
0&
#1750000
b1111 >
b11000110 (
b11000110 8
b1111 =
1&
#1800000
0&
#1850000
b10000 >
b11000101 (
b11000101 8
b10000 =
1&
#1900000
0&
#1950000
b10001 >
b10101010 (
b10101010 8
b10001 =
1&
#2000000
0&
#2050000
b10010 >
b11100101 (
b11100101 8
b10010 =
1&
#2100000
0&
#2150000
b10011 >
b1110111 (
b1110111 8
b10011 =
1&
#2200000
0&
#2250000
b10100 >
b10100 =
1&
